near_api/__init__.py
near_api/account.py
near_api/providers.py
near_api/serializer.py
near_api/signer.py
near_api/transactions.py
lzr_near_api_py-0.1.11.dist-info/LICENSE
lzr_near_api_py-0.1.11.dist-info/LICENSE-APACHE
lzr_near_api_py-0.1.11.dist-info/METADATA
lzr_near_api_py-0.1.11.dist-info/WHEEL
lzr_near_api_py-0.1.11.dist-info/top_level.txt
lzr_near_api_py-0.1.11.dist-info/RECORD
