Metadata-Version: 2.1
Name: lzr-near-api-py
Version: 0.1.11
Home-page: https://github.com/near/near-api-py
Author: NEAR Inc
License: MIT
License-File: LICENSE
License-File: LICENSE-APACHE
Requires-Dist: requests
Requires-Dist: urllib3
Requires-Dist: base58
Requires-Dist: ed25519
